<?xml version="1.0" encoding="utf-8" ?><dwsync><file name="folder-new.png" server="172.16.1.33//var/www/html/portalweb/" local="3556218018" remote="318763443949114530" Dst="-1" /><file name="volver_16.png" server="172.16.1.33//var/www/html/portalweb/" local="3556218018" remote="318763443949114530" Dst="-1" /><file name="next_16.png" server="172.16.1.33//var/www/html/portalweb/" local="3556218018" remote="318763443949114530" Dst="-1" /><file name="ok_16.png" server="172.16.1.33//var/www/html/portalweb/" local="3556218018" remote="318763443949114530" Dst="-1" /><file name="calendario_16.png" server="172.16.1.33//var/www/html/portalweb/" local="3556218018" remote="318763443949114530" Dst="-1" /><file name="star_seguimiento.png" server="172.16.1.33//var/www/html/portalweb/" local="3556218018" remote="318763443949114530" Dst="-1" /><file name="busqueda_32.png" server="172.16.1.33//var/www/html/portalweb/" local="3556218018" remote="318763443949114530" Dst="-1" /><file name=".DS_Store" server="172.16.1.33//var/www/html/portalweb/" local="3556218017" remote="318763443949114529" Dst="-1" /><file name="nook_16.png" server="172.16.1.33//var/www/html/portalweb/" local="3556218018" remote="318763443949114530" Dst="-1" /><file name="opciones_32.png" server="172.16.1.33//var/www/html/portalweb/" local="3556218018" remote="318763443949114530" Dst="-1" /><file name="volver_20.png" server="172.16.1.33//var/www/html/portalweb/" local="3556218018" remote="318763443949114530" Dst="-1" /><file name="old_16.png" server="172.16.1.33//var/www/html/portalweb/" local="3556218018" remote="318763443949114530" Dst="-1" /><file name="mensaje_20.png" server="172.16.1.33//var/www/html/portalweb/" local="3556218018" remote="318763443949114530" Dst="-1" /><file name="calendario_32.png" server="172.16.1.33//var/www/html/portalweb/" local="3556218018" remote="318763443949114530" Dst="-1" /><file name="folder-edit.png" server="172.16.1.33//var/www/html/portalweb/" local="3556218018" remote="318763443949114530" Dst="-1" /><file name="destroy_!6.png" server="172.16.1.33//var/www/html/portalweb/" local="3556218018" remote="318763443949114530" Dst="-1" /><file name="avance_20.png" server="172.16.1.33//var/www/html/portalweb/" local="3556218018" remote="318763443949114530" Dst="-1" /><file name="archivo_20.png" server="172.16.1.33//var/www/html/portalweb/" local="3556218017" remote="318763443949114529" Dst="-1" /><file name="destroy_16.png" server="172.16.1.33//var/www/html/portalweb/" local="3556218018" remote="318763443949114530" Dst="-1" /><file name=".DS_Store" server="172.16.1.33//var/www/html/seguimiento/" local="3556218017" remote="321525417181129565" Dst="-1" /><file name="archivo_20.png" server="172.16.1.33//var/www/html/seguimiento/" local="3556218017" remote="321525417181129565" Dst="-1" /><file name="avance_20.png" server="172.16.1.33//var/www/html/seguimiento/" local="3556218018" remote="321525417181129565" Dst="-1" /><file name="busqueda_32.png" server="172.16.1.33//var/www/html/seguimiento/" local="3556218018" remote="321525417181129565" Dst="-1" /><file name="calendario_16.png" server="172.16.1.33//var/www/html/seguimiento/" local="3556218018" remote="321525417181129565" Dst="-1" /><file name="calendario_32.png" server="172.16.1.33//var/www/html/seguimiento/" local="3556218018" remote="321525417181129565" Dst="-1" /><file name="destroy_!6.png" server="172.16.1.33//var/www/html/seguimiento/" local="3556218018" remote="321525417181129565" Dst="-1" /><file name="destroy_16.png" server="172.16.1.33//var/www/html/seguimiento/" local="3556218018" remote="321525417181129565" Dst="-1" /><file name="folder-edit.png" server="172.16.1.33//var/www/html/seguimiento/" local="3556218018" remote="321525417181129566" Dst="-1" /><file name="folder-new.png" server="172.16.1.33//var/www/html/seguimiento/" local="3556218018" remote="321525417181129566" Dst="-1" /><file name="mensaje_20.png" server="172.16.1.33//var/www/html/seguimiento/" local="3556218018" remote="321525417181129566" Dst="-1" /><file name="next_16.png" server="172.16.1.33//var/www/html/seguimiento/" local="3556218018" remote="321525417181129566" Dst="-1" /><file name="nook_16.png" server="172.16.1.33//var/www/html/seguimiento/" local="3556218018" remote="321525417181129566" Dst="-1" /><file name="ok_16.png" server="172.16.1.33//var/www/html/seguimiento/" local="3556218018" remote="321525417181129566" Dst="-1" /><file name="old_16.png" server="172.16.1.33//var/www/html/seguimiento/" local="3556218018" remote="321525417181129567" Dst="-1" /><file name="opciones_32.png" server="172.16.1.33//var/www/html/seguimiento/" local="3556218018" remote="321525417181129567" Dst="-1" /><file name="star_seguimiento.png" server="172.16.1.33//var/www/html/seguimiento/" local="3556218018" remote="321525417181129567" Dst="-1" /><file name="volver_16.png" server="172.16.1.33//var/www/html/seguimiento/" local="3556218018" remote="321525417181129567" Dst="-1" /><file name="volver_20.png" server="172.16.1.33//var/www/html/seguimiento/" local="3556218018" remote="321525417181129567" Dst="-1" /></dwsync>